CHANGELOG
LICENSE
MANIFEST.in
README.md
setup.py
yam/__init__.py
yam/commands.py
yam/conf_example.json
yam/correlate.py
yam/imaging.py
yam/io.py
yam/main.py
yam/stack.py
yam/stretch.py
yam/util.py
yam.egg-info/PKG-INFO
yam.egg-info/SOURCES.txt
yam.egg-info/dependency_links.txt
yam.egg-info/entry_points.txt
yam.egg-info/not-zip-safe
yam.egg-info/requires.txt
yam.egg-info/top_level.txt
yam/tests/__init__.py
yam/tests/__main__.py
yam/tests/test_correlate.py
yam/tests/test_main.py
yam/tests/test_stretch.py