Metadata-Version: 1.1
Name: yam
Version: 0.7.0
Summary: Yet another monitoring tool using correlations of ambient noise (seismology)
Home-page: https://github.com/trichter/yam
Author: Tom Eulenfeld
Author-email: tom.eulenfeld@gmail.de
License: MIT
Platform: UNKNOWN
Classifier: Environment :: Console
Classifier: Intended Audience :: Science/Research
Classifier: License :: OSI Approved :: GNU General Public License v3 (GPLv3)
Classifier: Operating System :: OS Independent
Classifier: Programming Language :: Python :: 3
Classifier: Programming Language :: Python :: 3.5
Classifier: Programming Language :: Python :: 3.6
Classifier: Programming Language :: Python :: 3.7
Classifier: Programming Language :: Python :: 3.8
Classifier: Topic :: Scientific/Engineering :: Physics
